photon_packet_parser/__init__.py
photon_packet_parser/byte_reader.py
photon_packet_parser/command_type.py
photon_packet_parser/crc_calculator.py
photon_packet_parser/event_data.py
photon_packet_parser/message_type.py
photon_packet_parser/number_serializer.py
photon_packet_parser/operation_request.py
photon_packet_parser/operation_response.py
photon_packet_parser/photon_packet_parser.py
photon_packet_parser/protocol16_deserializer.py
photon_packet_parser/protocol16_type.py
photon_packet_parser/segmented_package.py
photon_packet_parser-0.1.2.dist-info/LICENSE
photon_packet_parser-0.1.2.dist-info/METADATA
photon_packet_parser-0.1.2.dist-info/WHEEL
photon_packet_parser-0.1.2.dist-info/top_level.txt
photon_packet_parser-0.1.2.dist-info/RECORD
